{"chunk_definitions":[{"row":9,"row_count":1,"visible":true,"expansion_state":0,"options":{"engine":"r","label":"setup","include":false},"document_id":"50CD0F77","chunk_id":"csetup_chunk","chunk_label":"setup"},{"row":84,"row_count":1,"visible":true,"expansion_state":0,"options":{"engine":"r","label":"unnamed-chunk-44"},"document_id":"50CD0F77","chunk_id":"cykwzp6hf694e","chunk_label":"unnamed-chunk-1"},{"row":107,"row_count":1,"visible":true,"expansion_state":0,"options":{"engine":"r","label":"unnamed-chunk-37"},"document_id":"50CD0F77","chunk_id":"c466c9j8bh44c","chunk_label":"unnamed-chunk-2"},{"row":120,"row_count":1,"visible":true,"expansion_state":0,"options":{"engine":"r","label":"unnamed-chunk-39"},"document_id":"50CD0F77","chunk_id":"c0inohf32octm","chunk_label":"unnamed-chunk-3"},{"row":131,"row_count":1,"visible":true,"expansion_state":0,"options":{"engine":"r","label":"unnamed-chunk-45"},"document_id":"50CD0F77","chunk_id":"ctwdvgng4l3xe","chunk_label":"unnamed-chunk-4"},{"row":182,"row_count":1,"visible":true,"expansion_state":0,"options":{"engine":"r","label":"unnamed-chunk-59"},"document_id":"50CD0F77","chunk_id":"czvxs5m7cln64","chunk_label":"unnamed-chunk-5"},{"row":233,"row_count":1,"visible":true,"expansion_state":0,"options":{"engine":"r","label":"unnamed-chunk-58"},"document_id":"50CD0F77","chunk_id":"cysljwjti6n0t","chunk_label":"unnamed-chunk-6"}],"doc_write_time":1612885926,"working_dir":null,"default_chunk_options":{"echo":true}}